{
    "version": "1",
    "isInitialized": 1,
    "arenaObjectsConfigFile": "NWA",
    "playersCount": [
        1,
        2,
        3,
        4,
        5,
        6,
        7,
        8,
        9,
        10,
        15
    ],
    "roundsCount": [
        1,
        2,
        3,
        5,
        10
    ],
    "deathPenaltyTimeInSeconds": [
        1,
        2,
        3,
        5,
        10
    ],
    "maxTimePerRoundInMinutes": [
        5,
        10,
        15,
        30,
        60
    ],
    "maxKillsPerRound": [
        1,
        2,
        3,
        5,
        10,
        25,
        50,
        100
    ],
    "startingFee": [
        1000,
        2000,
        3000,
        5000,
        10000
    ],
    "teamWinRatio": [
        {
            "place": 1,
            "ratio": 0.5
        },
        {
            "place": 2,
            "ratio": 0.30000001192092898
        }
    ],
    "enableChangeSides": 1,
    "enableOneLifeMode": 1,
    "enableShowTeamMarker": 1,
    "enableStaminaMode": 1,
    "enableShowSpectatorMode": 1,
    "gearSetNames": [
        "Example1",
        "Example2"
    ],
    "gearSets": [],
    "externalPlayersCanEnterArena": 0,
    "adminCanEnterArena": 1,
    "enableMultipleGearSets": 1,
    "showArenaBoarderPoints": 1,
    "teamSpawnZones": {
        "1": [
            {
                "position": [
                    4634.9765625,
                    344.09503173828127,
                    10177.32421875
                ],
                "orientation": [
                    -16.062376022338868,
                    -0.0,
                    0.0
                ],
                "radius": 10.0
            },
            {
                "position": [
                    4635.69677734375,
                    344.1348876953125,
                    10187.4697265625
                ],
                "orientation": [
                    -134.8872833251953,
                    0.0,
                    -0.0
                ],
                "radius": 10.0
            },
            {
                "position": [
                    4635.974609375,
                    340.1194152832031,
                    10188.76171875
                ],
                "orientation": [
                    140.82240295410157,
                    0.0,
                    -0.0
                ],
                "radius": 10.0
            },
            {
                "position": [
                    4596.09716796875,
                    344.5137634277344,
                    10152.9580078125
                ],
                "orientation": [
                    -17.553936004638673,
                    -0.0,
                    0.0
                ],
                "radius": 10.0
            },
            {
                "position": [
                    4596.30078125,
                    340.4637451171875,
                    10159.5068359375
                ],
                "orientation": [
                    103.02496337890625,
                    0.0,
                    -0.0
                ],
                "radius": 10.0
            },
            {
                "position": [
                    4645.87939453125,
                    339.50091552734377,
                    10208.0322265625
                ],
                "orientation": [
                    141.726806640625,
                    0.0,
                    -0.0
                ],
                "radius": 10.0
            },
            {
                "position": [
                    4636.72998046875,
                    339.50933837890627,
                    10199.951171875
                ],
                "orientation": [
                    141.47206115722657,
                    0.0,
                    -0.0
                ],
                "radius": 10.0
            },
            {
                "position": [
                    4590.55712890625,
                    339.2329406738281,
                    10104.4423828125
                ],
                "orientation": [
                    -42.30949020385742,
                    -0.0,
                    0.0
                ],
                "radius": 10.0
            },
            {
                "position": [
                    4583.875,
                    339.2203369140625,
                    10101.078125
                ],
                "orientation": [
                    -45.40456008911133,
                    -0.0,
                    0.0
                ],
                "radius": 10.0
            },
            {
                "position": [
                    4595.9462890625,
                    339.26544189453127,
                    10095.1630859375
                ],
                "orientation": [
                    -36.458194732666019,
                    -0.0,
                    0.0
                ],
                "radius": 10.0
            },
            {
                "position": [
                    4590.21533203125,
                    339.2528076171875,
                    10092.0244140625
                ],
                "orientation": [
                    -51.97791290283203,
                    -0.0,
                    0.0
                ],
                "radius": 10.0
            },
            {
                "position": [
                    4583.57080078125,
                    339.2528381347656,
                    10088.8251953125
                ],
                "orientation": [
                    -0.21211256086826325,
                    -0.0,
                    0.0
                ],
                "radius": 10.0
            },
            {
                "position": [
                    4597.66357421875,
                    339.3734436035156,
                    10128.927734375
                ],
                "orientation": [
                    161.81825256347657,
                    0.0,
                    -0.0
                ],
                "radius": 10.0
            },
            {
                "position": [
                    4591.69921875,
                    339.2856750488281,
                    10125.17578125
                ],
                "orientation": [
                    146.6307830810547,
                    0.0,
                    -0.0
                ],
                "radius": 10.0
            },
            {
                "position": [
                    4679.74072265625,
                    339.504150390625,
                    10163.736328125
                ],
                "orientation": [
                    -119.01095581054688,
                    0.0,
                    -0.0
                ],
                "radius": 10.0
            },
            {
                "position": [
                    4677.7578125,
                    339.5118713378906,
                    10170.5947265625
                ],
                "orientation": [
                    -121.02952575683594,
                    0.0,
                    -0.0
                ],
                "radius": 10.0
            },
            {
                "position": [
                    4674.70654296875,
                    339.5153503417969,
                    10175.9306640625
                ],
                "orientation": [
                    -96.14677429199219,
                    0.0,
                    -0.0
                ],
                "radius": 10.0
            },
            {
                "position": [
                    4671.7099609375,
                    339.521240234375,
                    10181.9453125
                ],
                "orientation": [
                    -115.55459594726563,
                    0.0,
                    -0.0
                ],
                "radius": 10.0
            }
        ],
        "2": [
            {
                "position": [
                    4476.88232421875,
                    339.2348937988281,
                    10520.591796875
                ],
                "orientation": [
                    143.39718627929688,
                    0.0,
                    -0.0
                ],
                "radius": 10.0
            },
            {
                "position": [
                    4471.5595703125,
                    339.2469482421875,
                    10518.0791015625
                ],
                "orientation": [
                    136.7873077392578,
                    0.0,
                    -0.0
                ],
                "radius": 10.0
            },
            {
                "position": [
                    4468.7216796875,
                    339.2475280761719,
                    10516.095703125
                ],
                "orientation": [
                    161.55908203125,
                    0.0,
                    -0.0
                ],
                "radius": 10.0
            },
            {
                "position": [
                    4472.1708984375,
                    339.2340393066406,
                    10508.9189453125
                ],
                "orientation": [
                    140.3861083984375,
                    0.0,
                    -0.0
                ],
                "radius": 10.0
            },
            {
                "position": [
                    4478.03369140625,
                    339.2214050292969,
                    10512.236328125
                ],
                "orientation": [
                    159.5349578857422,
                    0.0,
                    -0.0
                ],
                "radius": 10.0
            },
            {
                "position": [
                    4484.357421875,
                    339.2214660644531,
                    10515.92578125
                ],
                "orientation": [
                    138.9562225341797,
                    0.0,
                    -0.0
                ],
                "radius": 10.0
            },
            {
                "position": [
                    4471.05810546875,
                    339.3971252441406,
                    10484.0625
                ],
                "orientation": [
                    -24.502477645874025,
                    -0.0,
                    0.0
                ],
                "radius": 10.0
            },
            {
                "position": [
                    4476.978515625,
                    339.32196044921877,
                    10486.779296875
                ],
                "orientation": [
                    -33.24567413330078,
                    -0.0,
                    0.0
                ],
                "radius": 10.0
            },
            {
                "position": [
                    4465.3291015625,
                    339.4732360839844,
                    10481.119140625
                ],
                "orientation": [
                    -28.66707420349121,
                    -0.0,
                    0.0
                ],
                "radius": 10.0
            },
            {
                "position": [
                    4385.1884765625,
                    339.4234924316406,
                    10443.875
                ],
                "orientation": [
                    67.01822662353516,
                    0.0,
                    -0.0
                ],
                "radius": 10.0
            },
            {
                "position": [
                    4386.712890625,
                    339.43133544921877,
                    10437.671875
                ],
                "orientation": [
                    43.41303253173828,
                    0.0,
                    -0.0
                ],
                "radius": 10.0
            },
            {
                "position": [
                    4391.0068359375,
                    339.4286193847656,
                    10432.322265625
                ],
                "orientation": [
                    43.41303253173828,
                    0.0,
                    -0.0
                ],
                "radius": 10.0
            },
            {
                "position": [
                    4393.80224609375,
                    339.440185546875,
                    10427.0771484375
                ],
                "orientation": [
                    43.10710144042969,
                    0.0,
                    -0.0
                ],
                "radius": 10.0
            },
            {
                "position": [
                    4416.31640625,
                    339.2314147949219,
                    10398.134765625
                ],
                "orientation": [
                    -44.278316497802737,
                    -0.0,
                    0.0
                ],
                "radius": 10.0
            },
            {
                "position": [
                    4421.6318359375,
                    339.4488830566406,
                    10401.662109375
                ],
                "orientation": [
                    -36.265201568603519,
                    -0.0,
                    0.0
                ],
                "radius": 10.0
            },
            {
                "position": [
                    4426.71435546875,
                    339.63720703125,
                    10405.1787109375
                ],
                "orientation": [
                    -37.88046646118164,
                    -0.0,
                    0.0
                ],
                "radius": 10.0
            },
            {
                "position": [
                    4431.49658203125,
                    339.6424865722656,
                    10409.98046875
                ],
                "orientation": [
                    -43.47774887084961,
                    -0.0,
                    0.0
                ],
                "radius": 10.0
            },
            {
                "position": [
                    4431.43701171875,
                    344.271728515625,
                    10435.27734375
                ],
                "orientation": [
                    164.1773223876953,
                    0.0,
                    -0.0
                ],
                "radius": 10.0
            },
            {
                "position": [
                    4442.56298828125,
                    344.2716369628906,
                    10430.3603515625
                ],
                "orientation": [
                    -121.13890075683594,
                    0.0,
                    -0.0
                ],
                "radius": 10.0
            },
            {
                "position": [
                    4469.3134765625,
                    344.3312072753906,
                    10458.0849609375
                ],
                "orientation": [
                    133.96839904785157,
                    0.0,
                    -0.0
                ],
                "radius": 10.0
            },
            {
                "position": [
                    4478.06787109375,
                    340.2611999511719,
                    10453.4130859375
                ],
                "orientation": [
                    -130.811279296875,
                    0.0,
                    -0.0
                ],
                "radius": 10.0
            }
        ]
    },
    "teamsCount": [],
    "playerHealth": 100,
    "playerShield": 100,
    "startCountdown": 60,
    "startNextRoundCountdown": 20,
    "endMatchCountdown": 10
}